LICENSE.txt
MANIFEST.in
setup.cfg
setup.py
pymazonian/__init__.py
pymazonian/mws.py
pymazonian/offamazonpayments.py
pymazonian/utils.py
pymazonian.egg-info/PKG-INFO
pymazonian.egg-info/SOURCES.txt
pymazonian.egg-info/dependency_links.txt
pymazonian.egg-info/not-zip-safe
pymazonian.egg-info/requires.txt
pymazonian.egg-info/top_level.txt